toolchest_client/__init__.py
toolchest_client/api/__init__.py
toolchest_client/api/auth.py
toolchest_client/api/download.py
toolchest_client/api/exceptions.py
toolchest_client/api/instance_type.py
toolchest_client/api/output.py
toolchest_client/api/query.py
toolchest_client/api/status.py
toolchest_client/api/streaming.py
toolchest_client/api/urls.py
toolchest_client/cli/__init__.py
toolchest_client/cli/cli.py
toolchest_client/cli/kraken2.py
toolchest_client/cli/test.py
toolchest_client/files/__init__.py
toolchest_client/files/general.py
toolchest_client/files/merge.py
toolchest_client/files/public_uris.py
toolchest_client/files/s3.py
toolchest_client/files/split.py
toolchest_client/files/tests/__init__.py
toolchest_client/files/tests/data/eight_line.fastq
toolchest_client/files/tests/data/eight_line_split_one.fastq
toolchest_client/files/tests/data/eight_line_split_two.fastq
toolchest_client/files/tests/data/paired_end/eight_line_R1.fastq
toolchest_client/files/tests/data/paired_end/eight_line_R2.fastq
toolchest_client/files/tests/data/very_small_file.txt
toolchest_client/files/tests/test_general.py
toolchest_client/files/tests/test_merge.py
toolchest_client/files/tests/test_s3.py
toolchest_client/files/tests/test_split.py
toolchest_client/files/unpack.py
toolchest_client/logging.py
toolchest_client/tools/__init__.py
toolchest_client/tools/alphafold.py
toolchest_client/tools/api.py
toolchest_client/tools/blastn.py
toolchest_client/tools/bowtie2.py
toolchest_client/tools/bracken.py
toolchest_client/tools/cellranger.py
toolchest_client/tools/centrifuge.py
toolchest_client/tools/clustalo.py
toolchest_client/tools/demucs.py
toolchest_client/tools/diamond.py
toolchest_client/tools/fastqc.py
toolchest_client/tools/humann.py
toolchest_client/tools/jupyter.py
toolchest_client/tools/kallisto.py
toolchest_client/tools/kraken2.py
toolchest_client/tools/last.py
toolchest_client/tools/lug.py
toolchest_client/tools/megahit.py
toolchest_client/tools/metaphlan.py
toolchest_client-0.11.14.dist-info/entry_points.txt
toolchest_client-0.11.14.dist-info/WHEEL
toolchest_client-0.11.14.dist-info/METADATA
toolchest_client-0.11.14.dist-info/LICENSE
toolchest_client-0.11.14.dist-info/RECORD
