Metadata-Version: 2.1
Name: toolchest-client
Version: 0.11.14
Summary: Python client for Toolchest
Home-page: https://github.com/trytoolchest/toolchest-client-python
License: AGPL-3.0-only
Author: Justin Herr
Author-email: justin@trytoolchest.com
Requires-Python: >=3.7,<4.0
Classifier: License :: OSI Approved :: GNU Affero General Public License v3
Classifier: Operating System :: OS Independent
Classifier: Programming Language :: Python :: 3
Classifier: Programming Language :: Python :: 3.7
Classifier: Programming Language :: Python :: 3.8
Classifier: Programming Language :: Python :: 3.9
Classifier: Programming Language :: Python :: 3.10
Classifier: Programming Language :: Python :: 3.11
Classifier: Programming Language :: Python :: 3
Requires-Dist: boto3 (>=1.18.29,<2.0.0)
Requires-Dist: docker (>=6.0.0,<7.0.0)
Requires-Dist: importlib-metadata (>=4.2,<5.0)
Requires-Dist: loguru (>=0.6.0,<0.7.0)
Requires-Dist: python-dotenv (>=0.20.0,<0.21.0)
Requires-Dist: requests (>=2.25.1,<3.0.0)
Requires-Dist: typer (>=0.4.1,<0.5.0)
Requires-Dist: websockets (>=10.3,<11.0)
Project-URL: Bug Tracker, https://github.com/trytoolchest/toolchest-client-python/issues
Project-URL: Documentation, https://docs.trytoolchest.com/
Project-URL: Repository, https://github.com/trytoolchest/toolchest-client-python
